.coveragerc
.editorconfig
.travis.yml
CHANGES.rst
CONTRIBUTORS.rst
LICENSE
MANIFEST.in
README.rst
bootstrap-buildout.py
buildout.cfg
setup.cfg
setup.py
travis.cfg
docs/LICENSE.GPL
docs/LICENSE.rst
docs/index.rst
src/collective/.DS_Store
src/collective/__init__.py
src/collective.filemeta.egg-info/PKG-INFO
src/collective.filemeta.egg-info/SOURCES.txt
src/collective.filemeta.egg-info/dependency_links.txt
src/collective.filemeta.egg-info/entry_points.txt
src/collective.filemeta.egg-info/namespace_packages.txt
src/collective.filemeta.egg-info/not-zip-safe
src/collective.filemeta.egg-info/requires.txt
src/collective.filemeta.egg-info/top_level.txt
src/collective/filemeta/.DS_Store
src/collective/filemeta/__init__.py
src/collective/filemeta/base.py
src/collective/filemeta/behaviors.py
src/collective/filemeta/configure.zcml
src/collective/filemeta/content.py
src/collective/filemeta/interfaces.py
src/collective/filemeta/model.xml
src/collective/filemeta/setuphandlers.py
src/collective/filemeta/subscribers.py
src/collective/filemeta/testing.py
src/collective/filemeta/utilities.py
src/collective/filemeta/browser/__init__.py
src/collective/filemeta/browser/configure.zcml
src/collective/filemeta/browser/templates.pt
src/collective/filemeta/browser/views.py
src/collective/filemeta/browser/overrides/.gitkeep
src/collective/filemeta/browser/static/.gitkeep
src/collective/filemeta/browser/static/styles.css
src/collective/filemeta/locales/collective.documentfile.pot
src/collective/filemeta/locales/update.sh
src/collective/filemeta/profiles/default/browserlayer.xml
src/collective/filemeta/profiles/default/metadata.xml
src/collective/filemeta/profiles/exampletype/browserlayer.xml
src/collective/filemeta/profiles/exampletype/metadata.xml
src/collective/filemeta/profiles/exampletype/types.xml
src/collective/filemeta/profiles/exampletype/types/DocumentFile.xml
src/collective/filemeta/profiles/extendedfile/browserlayer.xml
src/collective/filemeta/profiles/extendedfile/metadata.xml
src/collective/filemeta/profiles/extendedfile/types.xml
src/collective/filemeta/profiles/extendedfile/types/File.xml
src/collective/filemeta/profiles/uninstall/browserlayer.xml
src/collective/filemeta/tests/__init__.py
src/collective/filemeta/tests/test_documentfile.py
src/collective/filemeta/tests/test_robot.py
src/collective/filemeta/tests/test_setup.py
