Metadata-Version: 1.1
Name: collective.filemeta
Version: 1.0rc1
Summary: Document file (MS Office etc.)
Home-page: https://pypi.python.org/pypi/collective.filemeta
Author: Petri Savolainen
Author-email: petri.savolainen@koodaamo.fi
License: GPL version 2
Keywords: Python Plone
Platform: UNKNOWN
Classifier: Environment :: Web Environment
Classifier: Framework :: Plone
Classifier: Framework :: Plone :: 4.3
Classifier: Programming Language :: Python
Classifier: Programming Language :: Python :: 2.7
Classifier: Operating System :: OS Independent
Classifier: License :: OSI Approved :: GNU General Public License v2 (GPLv2)
